vodem/__init__.py
vodem/api.py
vodem/connection.py
vodem/exceptions.py
vodem/simple.py
vodem/util.py
zte_mf823-0.0.1.dev21.dist-info/AUTHORS
zte_mf823-0.0.1.dev21.dist-info/LICENSE
zte_mf823-0.0.1.dev21.dist-info/METADATA
zte_mf823-0.0.1.dev21.dist-info/WHEEL
zte_mf823-0.0.1.dev21.dist-info/pbr.json
zte_mf823-0.0.1.dev21.dist-info/top_level.txt
zte_mf823-0.0.1.dev21.dist-info/RECORD
