Metadata-Version: 2.1
Name: zte-mf823
Version: 0.0.1.dev21
Summary: Vodafone Vodafone K4607-Z web interface python bindings
Home-page: http://pypi.python.org/pypi/vodem-vodafone-K4607-Z
Author: alzeih
Author-email: alzeih@users.noreply.github.com
License: UNKNOWN
Platform: UNKNOWN
Classifier: Development Status :: 3 - Alpha
Classifier: Operating System :: OS Independent
Classifier: License :: OSI Approved :: MIT License
Classifier: Topic :: Communications :: Telephony
Classifier: Programming Language :: Python
Classifier: Programming Language :: Python :: 3 :: Only
Classifier: Programming Language :: Python :: 3.5
Requires-Dist: requests
Requires-Dist: pbr
Requires-Dist: wheel
Provides-Extra: dev
Requires-Dist: pylint ; extra == 'dev'
Requires-Dist: sphinx ; extra == 'dev'
